whatsapp_sdk/__init__.py
whatsapp_sdk/client.py
whatsapp_sdk/config.py
whatsapp_sdk/exceptions.py
whatsapp_sdk/http_client.py
whatsapp_sdk/models/__init__.py
whatsapp_sdk/models/base.py
whatsapp_sdk/models/contacts.py
whatsapp_sdk/models/media.py
whatsapp_sdk/models/messages.py
whatsapp_sdk/models/templates.py
whatsapp_sdk/models/webhooks.py
whatsapp_sdk/services/__init__.py
whatsapp_sdk/services/media.py
whatsapp_sdk/services/messages.py
whatsapp_sdk/services/templates.py
whatsapp_sdk/services/webhooks.py
whatsapp_sdk-0.2.0.dist-info/licenses/LICENSE
whatsapp_sdk-0.2.0.dist-info/METADATA
whatsapp_sdk-0.2.0.dist-info/WHEEL
whatsapp_sdk-0.2.0.dist-info/top_level.txt
whatsapp_sdk-0.2.0.dist-info/RECORD
