Metadata-Version: 2.4
Name: whatsapp-sdk
Version: 0.2.0
Summary: A comprehensive synchronous Python SDK for WhatsApp Business Cloud API following Meta's official documentation
Author-email: Alejandro Velez <alejandro-243@hotmail.com>
Maintainer-email: Alejandro Velez <alejandro-243@hotmail.com>
License: MIT
Project-URL: Homepage, https://github.com/alejandrovelez243/whatsapp-sdk
Project-URL: Documentation, https://whatsapp-sdk.readthedocs.io
Project-URL: Repository, https://github.com/alejandrovelez243/whatsapp-sdk
Project-URL: Bug Tracker, https://github.com/alejandrovelez243/whatsapp-sdk/issues
Project-URL: Changelog, https://github.com/alejandrovelez243/whatsapp-sdk/blob/main/CHANGELOG.md
Keywords: whatsapp,whatsapp-business,sdk,api,meta,cloud-api,messaging,chatbot,business-messaging
Classifier: Development Status :: 3 - Alpha
Classifier: Intended Audience :: Developers
Classifier: License :: OSI Approved :: MIT License
Classifier: Operating System :: OS Independent
Classifier: Programming Language :: Python
Classifier: Programming Language :: Python :: 3
Classifier: Programming Language :: Python :: 3.8
Classifier: Programming Language :: Python :: 3.9
Classifier: Programming Language :: Python :: 3.10
Classifier: Programming Language :: Python :: 3.11
Classifier: Programming Language :: Python :: 3.12
Classifier: Topic :: Communications :: Chat
Classifier: Topic :: Software Development :: Libraries :: Python Modules
Classifier: Topic :: Internet :: WWW/HTTP
Classifier: Typing :: Typed
Classifier: Natural Language :: English
Classifier: Natural Language :: Spanish
Requires-Python: >=3.8
License-File: LICENSE
Requires-Dist: httpx>=0.25.0
Requires-Dist: pydantic>=2.0.0
Requires-Dist: cryptography>=41.0.0
Requires-Dist: python-dotenv>=1.0.0
Requires-Dist: typing-extensions>=4.8.0; python_version < "3.10"
Provides-Extra: fastapi
Requires-Dist: fastapi>=0.100.0; extra == "fastapi"
Requires-Dist: python-multipart>=0.0.6; extra == "fastapi"
Provides-Extra: dev
Requires-Dist: pytest>=7.4.0; extra == "dev"
Requires-Dist: pytest-asyncio>=0.21.0; extra == "dev"
Requires-Dist: pytest-cov>=4.1.0; extra == "dev"
Requires-Dist: pytest-mock>=3.11.0; extra == "dev"
Requires-Dist: black>=23.7.0; extra == "dev"
Requires-Dist: ruff>=0.1.0; extra == "dev"
Requires-Dist: mypy>=1.5.0; extra == "dev"
Requires-Dist: pre-commit>=3.3.0; extra == "dev"
Requires-Dist: mkdocs>=1.5.0; extra == "dev"
Requires-Dist: mkdocs-material>=9.2.0; extra == "dev"
Requires-Dist: mkdocstrings[python]>=0.23.0; extra == "dev"
Dynamic: license-file
